pyarrow/acero.py
pyarrow/array.pxi
pyarrow/arrow.dll
pyarrow/arrow.lib
pyarrow/arrow_acero.dll
pyarrow/arrow_acero.lib
pyarrow/arrow_compute.dll
pyarrow/arrow_compute.lib
pyarrow/arrow_dataset.dll
pyarrow/arrow_dataset.lib
pyarrow/arrow_flight.dll
pyarrow/arrow_flight.lib
pyarrow/arrow_python.dll
pyarrow/arrow_python.lib
pyarrow/arrow_python_flight.dll
pyarrow/arrow_python_flight.lib
pyarrow/arrow_python_parquet_encryption.dll
pyarrow/arrow_python_parquet_encryption.lib
pyarrow/arrow_substrait.dll
pyarrow/arrow_substrait.lib
pyarrow/benchmark.pxi
pyarrow/benchmark.py
pyarrow/builder.pxi
pyarrow/cffi.py
pyarrow/compat.pxi
pyarrow/compute.py
pyarrow/config.pxi
pyarrow/conftest.py
pyarrow/csv.py
pyarrow/cuda.py
pyarrow/dataset.py
pyarrow/device.pxi
pyarrow/error.pxi
pyarrow/feather.py
pyarrow/flight.py
pyarrow/fs.py
pyarrow/gandiva.pyx
pyarrow/io.pxi
pyarrow/ipc.pxi
pyarrow/ipc.py
pyarrow/json.py
pyarrow/jvm.py
pyarrow/lib.cp313-win_amd64.pyd
pyarrow/lib.h
pyarrow/lib.pxd
pyarrow/lib.pyx
pyarrow/lib_api.h
pyarrow/memory.pxi
pyarrow/orc.py
pyarrow/pandas-shim.pxi
pyarrow/pandas_compat.py
pyarrow/parquet.dll
pyarrow/parquet.lib
pyarrow/public-api.pxi
pyarrow/scalar.pxi
pyarrow/substrait.py
pyarrow/table.pxi
pyarrow/tensor.pxi
pyarrow/types.pxi
pyarrow/types.py
pyarrow/util.py
pyarrow/_acero.cp313-win_amd64.pyd
pyarrow/_acero.pxd
pyarrow/_acero.pyx
pyarrow/_azurefs.pyx
pyarrow/_compute.cp313-win_amd64.pyd
pyarrow/_compute.pxd
pyarrow/_compute.pyx
pyarrow/_compute_docstrings.py
pyarrow/_csv.cp313-win_amd64.pyd
pyarrow/_csv.pxd
pyarrow/_csv.pyx
pyarrow/_cuda.pxd
pyarrow/_cuda.pyx
pyarrow/_dataset.cp313-win_amd64.pyd
pyarrow/_dataset.pxd
pyarrow/_dataset.pyx
pyarrow/_dataset_orc.cp313-win_amd64.pyd
pyarrow/_dataset_orc.pyx
pyarrow/_dataset_parquet.cp313-win_amd64.pyd
pyarrow/_dataset_parquet.pxd
pyarrow/_dataset_parquet.pyx
pyarrow/_dataset_parquet_encryption.cp313-win_amd64.pyd
pyarrow/_dataset_parquet_encryption.pyx
pyarrow/_dlpack.pxi
pyarrow/_feather.cp313-win_amd64.pyd
pyarrow-22.0.0.dist-info/DELVEWHEEL
pyarrow-22.0.0.dist-info/METADATA
pyarrow-22.0.0.dist-info/RECORD
pyarrow-22.0.0.dist-info/top_level.txt
pyarrow-22.0.0.dist-info/WHEEL
pyarrow-22.0.0.dist-info/licenses/LICENSE.txt
pyarrow-22.0.0.dist-info/licenses/NOTICE.txt
