Metadata-Version: 2.4
Name: pyarrow
Version: 22.0.0
Summary: Python library for Apache Arrow
Maintainer-email: Apache Arrow Developers <dev@arrow.apache.org>
License: Apache Software License
Project-URL: Homepage, https://arrow.apache.org/
Project-URL: Documentation, https://arrow.apache.org/docs/python
Project-URL: Repository, https://github.com/apache/arrow
Project-URL: Issues, https://github.com/apache/arrow/issues
Classifier: License :: OSI Approved :: Apache Software License
Classifier: Programming Language :: Python :: 3.10
Classifier: Programming Language :: Python :: 3.11
Classifier: Programming Language :: Python :: 3.12
Classifier: Programming Language :: Python :: 3.13
Classifier: Programming Language :: Python :: 3.14
Classifier: Programming Language :: Python :: Free Threading :: 2 - Beta
Requires-Python: >=3.10
Dynamic: license-file
